statistics_canada-2025.6.12.201824.dist-info/licenses/LICENSE
statscan/__init__.py
statscan/_version.py
statscan/dguid.py
statscan/py.typed
statscan/url.py
statscan/enums/frequency.py
statscan/enums/schema.py
statscan/enums/vintage.py
statscan/enums/auto/__init__.py
statscan/enums/auto/census_consolidated_subdivision.py
statscan/enums/auto/census_division.py
statscan/enums/auto/census_metropolitan_area.py
statscan/enums/auto/census_subdivision.py
statscan/enums/auto/census_tract.py
statscan/enums/auto/designated_place.py
statscan/enums/auto/economic_region.py
statscan/enums/auto/federal_electoral_district.py
statscan/enums/auto/province_territory.py
statscan/enums/geocode/cd_geocode.py
statscan/enums/geocode/cma_geocode.py
statscan/enums/geocode/geocode.py
statscan/enums/geocode/pr_geocode.py
statscan/util/data.py
statscan/util/log.py
statistics_canada-2025.6.12.201824.dist-info/METADATA
statistics_canada-2025.6.12.201824.dist-info/WHEEL
statistics_canada-2025.6.12.201824.dist-info/top_level.txt
statistics_canada-2025.6.12.201824.dist-info/RECORD
