Metadata-Version: 2.4
Name: statistics-canada
Version: 2025.6.12.201824
Summary: Python bindings for the Statistics Canada Web Data Service (WDS) API
Author-email: Paul Bouillon <pbouill@gmail.com>
License-Expression: GPL-3.0-or-later
Project-URL: Homepage, https://github.com/pbouill/statistics-canada
Project-URL: Repository, https://github.com/pbouill/statistics-canada.git
Project-URL: Bug Tracker, https://github.com/pbouill/statistics-canada/issues
Keywords: python,statistics,census,canada
Classifier: Development Status :: 3 - Alpha
Classifier: Programming Language :: Python :: 3
Classifier: Programming Language :: Python :: 3.11
Classifier: Programming Language :: Python :: 3.12
Classifier: Programming Language :: Python :: 3.13
Classifier: Operating System :: OS Independent
Requires-Python: >=3.11
License-File: LICENSE
Requires-Dist: httpx>=0.28.1
Requires-Dist: pandas>=2.3.0
Dynamic: license-file
